youngamerica/__init__.py
youngamerica/admin.py
youngamerica/apps.py
youngamerica/models.py
django_young_america-0.15.dist-info/METADATA
django_young_america-0.15.dist-info/WHEEL
django_young_america-0.15.dist-info/top_level.txt
django_young_america-0.15.dist-info/RECORD
