Metadata-Version: 2.1
Name: django-young-america
Version: 0.15
Summary: Django Young America service
Home-page: UNKNOWN
Author: 
Author-email: 
License: MIT
Platform: UNKNOWN
Requires-Dist: django
Requires-Dist: xmltodict
Requires-Dist: zeep
Requires-Dist: dicttoxml
